coininfo/__init__.py
coininfo/humain.py
coininfo/human.py
coininfo/info.py
coininfo/test_info.py
coininfo_einherer-0.1.3.dist-info/METADATA
coininfo_einherer-0.1.3.dist-info/WHEEL
coininfo_einherer-0.1.3.dist-info/top_level.txt
coininfo_einherer-0.1.3.dist-info/RECORD
