Metadata-Version: 2.1
Name: coininfo-einherer
Version: 0.1.3
Requires-Dist: requests ==2.31.0
